scrapy_hcf/__init__.py
scrapy_hcf/middleware.py
scrapy_hcf-1.0.0.dist-info/DESCRIPTION.rst
scrapy_hcf-1.0.0.dist-info/METADATA
scrapy_hcf-1.0.0.dist-info/RECORD
scrapy_hcf-1.0.0.dist-info/WHEEL
scrapy_hcf-1.0.0.dist-info/metadata.json
scrapy_hcf-1.0.0.dist-info/top_level.txt
