Metadata-Version: 2.0
Name: scrapy-hcf
Version: 1.0.0
Summary: Scrapy spider middleware to use Scrapinghub's Hub Crawl Frontier as a backend for URLs
Home-page: http://github.com/scrapy-plugins/scrapy-hcf
Author: Scrapinghub
Author-email: info@scrapinghub.com
License: BSD
Platform: Any
Classifier: Development Status :: 4 - Beta
Classifier: License :: OSI Approved :: BSD License
Classifier: Operating System :: OS Independent
Classifier: Programming Language :: Python
Classifier: Programming Language :: Python :: 2
Classifier: Programming Language :: Python :: 2.7
Classifier: Programming Language :: Python :: 3
Classifier: Programming Language :: Python :: 3.5
Requires-Dist: hubstorage
Requires-Dist: scrapinghub
Requires-Dist: scrapy
